znbdownload/__init__.py
znbdownload/admin.py
znbdownload/apps.py
znbdownload/fields.py
znbdownload/models.py
znbdownload/storage.py
znbdownload/urls.py
znbdownload/views.py
znbdownload/__pycache__/__init__.cpython-37.pyc
znbdownload/__pycache__/admin.cpython-37.pyc
znbdownload/__pycache__/apps.cpython-37.pyc
znbdownload/__pycache__/fields.cpython-37.pyc
znbdownload/__pycache__/models.cpython-37.pyc
znbdownload/__pycache__/storage.cpython-37.pyc
znbdownload/__pycache__/urls.cpython-37.pyc
znbdownload/__pycache__/views.cpython-37.pyc
znbdownload/management/commands/znbdownload_permission.py
znbdownload/management/commands/znbdownload_presigned_url.py
znbdownload/management/commands/__pycache__/znbdownload_permission.cpython-37.pyc
znbdownload/management/commands/__pycache__/znbdownload_presigned_url.cpython-37.pyc
znbdownload/management/commands/__pycache__/znbdownload_test.cpython-37.pyc
znbdownload/migrations/0001_initial.py
znbdownload/migrations/0002_privatedownload.py
znbdownload/migrations/__init__.py
znbdownload/migrations/__pycache__/0001_initial.cpython-37.pyc
znbdownload/migrations/__pycache__/0002_privatedownload.cpython-37.pyc
znbdownload/migrations/__pycache__/__init__.cpython-37.pyc
znbdownload/templates/znbdownload/secret_file.html
znbdownload/templatetags/znbdownload_tags.py
znbdownload/templatetags/__pycache__/znbdownload_tags.cpython-37.pyc
znbdownload-0.1.dist-info/AUTHORS
znbdownload-0.1.dist-info/LICENSE
znbdownload-0.1.dist-info/METADATA
znbdownload-0.1.dist-info/WHEEL
znbdownload-0.1.dist-info/top_level.txt
znbdownload-0.1.dist-info/RECORD
