Metadata-Version: 2.1
Name: znbdownload
Version: 0.1
Summary: A Django storage backend with versioning and S3 support.
Home-page: https://github.com/alexisbellido/znbdownload
Author: Alexis Bellido
Author-email: a@zinibu.com
License: BSD, see LICENSE file
Platform: UNKNOWN
Classifier: Environment :: Web Environment
Classifier: Framework :: Django
Classifier: Framework :: Django :: 2.0
Classifier: Framework :: Django :: 2.1
Classifier: Framework :: Django :: 2.2
Classifier: Intended Audience :: Developers
Classifier: License :: OSI Approved :: BSD License
Classifier: Operating System :: OS Independent
Classifier: Programming Language :: Python
Classifier: Programming Language :: Python :: 3
Classifier: Programming Language :: Python :: 3.4
Classifier: Programming Language :: Python :: 3.5
Classifier: Programming Language :: Python :: 3.6
Classifier: Programming Language :: Python :: 3.7
Requires-Python: >=3
Requires-Dist: Django (>=2.0)
Requires-Dist: boto3 (<2,>=1.9.70)
Requires-Dist: django-storages (<2,>=1.7.1)
